gdl3/Entity.py
gdl3/Events.py
gdl3/__init__.py
gdl3/shapes.py
gdl3/window.py
GDL3-0.0.1.dist-info/METADATA
GDL3-0.0.1.dist-info/WHEEL
GDL3-0.0.1.dist-info/top_level.txt
GDL3-0.0.1.dist-info/RECORD
