Metadata-Version: 2.1
Name: GDL3
Version: 0.0.1
Summary: Game Development Package
Author: ProgrammingBro (Akhil Ganta)
Author-email: <srinivasganta123@gmail.com>
Classifier: Development Status :: 1 - Planning
Classifier: Intended Audience :: Developers
Classifier: Programming Language :: Python :: 3
Classifier: Operating System :: Unix
Classifier: Operating System :: MacOS :: MacOS X
Classifier: Operating System :: Microsoft :: Windows
Requires-Dist: pygame
